tinynmc/__init__.py
tinynmc/tinynmc.py
tinynmc-0.2.0.dist-info/LICENSE
tinynmc-0.2.0.dist-info/METADATA
tinynmc-0.2.0.dist-info/WHEEL
tinynmc-0.2.0.dist-info/top_level.txt
tinynmc-0.2.0.dist-info/RECORD
